image_tools/__init__.py
image_tools/args.py
image_tools/bake.py
image_tools/completions.py
image_tools/lib.py
image_tools/preflight.py
image_tools/test_generate_bakefile.py
image_tools/version.py
image_tools/test/conf.py
image_tools_stackabletech-0.0.17.dist-info/licenses/LICENSE
image_tools_stackabletech-0.0.17.dist-info/METADATA
image_tools_stackabletech-0.0.17.dist-info/WHEEL
image_tools_stackabletech-0.0.17.dist-info/entry_points.txt
image_tools_stackabletech-0.0.17.dist-info/top_level.txt
image_tools_stackabletech-0.0.17.dist-info/RECORD
