Metadata-Version: 2.4
Name: image-tools-stackabletech
Version: 0.0.17
Summary: Image tools for the Stackable Data Platform.
Author-email: Razvan Mihai <razvan.mihai@stackable.tech>
Project-URL: Homepage, https://github.com/stackabletech/image-tools
Project-URL: Bug Tracker, https://github.com/stackabletech/image-tools/issues
Classifier: Programming Language :: Python :: 3
Classifier: License :: OSI Approved :: MIT License
Classifier: Operating System :: OS Independent
Requires-Python: >=3.10
License-File: LICENSE
Requires-Dist: Jinja2>=3.1.2
Requires-Dist: PyYAML>=6.0
Provides-Extra: lint
Requires-Dist: ruff>=0.5; extra == "lint"
Requires-Dist: mypy>=1.10; extra == "lint"
Provides-Extra: publish
Requires-Dist: twine>=5.0; extra == "publish"
Requires-Dist: build>=1.2; extra == "publish"
Dynamic: license-file
